windowsxpll/__init__.py
windowsxpll/projects/__init__.py
windowsxpll/projects/dimension_reduction.py
windowsxpll/projects/main_stand.py
windowsxpll/root/__init__.py
windowsxpll/root/model_automl_with_auto_dt.py
windowsxpll/src/__init__.py
windowsxpll/src/config.py
windowsxpll/src/evaluation.py
windowsxpll/src/feature_engineering.py
windowsxpll/src/feature_processor.py
windowsxpll/src/model_automl.py
windowsxpll/src/model_ensemble.py
windowsxpll/src/model_stacking.py
windowsxpll/src/model_tuning.py
windowsxpll/src/model_wq.py
windowsxpll-0.1.0.dist-info/METADATA
windowsxpll-0.1.0.dist-info/WHEEL
windowsxpll-0.1.0.dist-info/entry_points.txt
windowsxpll-0.1.0.dist-info/top_level.txt
windowsxpll-0.1.0.dist-info/RECORD
