Metadata-Version: 2.4
Name: windowsxpll
Version: 0.1.0
Summary: A comprehensive machine learning pipeline toolkit for feature engineering and model training
Author-email: Your Name <your.email@example.com>
License: MIT
Keywords: machine-learning,pipeline,feature-engineering
Classifier: Development Status :: 4 - Beta
Classifier: License :: OSI Approved :: MIT License
Classifier: Programming Language :: Python :: 3.10
Requires-Python: >=3.10
Requires-Dist: matplotlib>=3.10.7
Requires-Dist: optuna>=4.6.0
Requires-Dist: pandas>=2.3.3
Requires-Dist: scikit-learn>=1.7.2
Requires-Dist: seaborn>=0.13.2
Requires-Dist: xgboost>=3.1.2
Requires-Dist: optbinning==0.21.0
